{"id": "20230329_782_やっぽ", "from_name": "金城碧海", "from_addr": "sky_kinjo_jo1@mail.jo1.jp", "subject": "やっぽ", "date": "2023-03-29T12:37:46+09:00", "date_ts": 1680061066.0, "preview": "やっぽ 最近お絵描きしてないなぁ〜 たまにしたくなる！", "has_attachments": false, "attachments": [], "body_html": " \r\n                             \r\n                            \r\n                            <div id=\"wrap\" style=\"width:100%;margin:0; padding:0; background-color:#ffffff; color:#333333; font-family:sans-serif;text-align:center; line-height:1.7;\">\r\n                            <div id=\"container\" style=\"width:90%; height:auto; background-color:#FFFFFF; margin:0 auto; padding:30px 0; text-align:left;\"><div><img src=\"assets/20230329_782_やっぽ/e206423b27ab064c1e.jpeg\" style=\"max-width: 100%;\"></div>\r\n<div dir=\"auto\">最近お絵描きしてないなぁ〜</div>\r\n<div dir=\"auto\">たまにしたくなる！</div>\r\n\r\n</div></div>\r\n"}