{"id": "20250927_2583____", "from_name": "金城碧海", "from_addr": "sky_kinjo_jo1@mail.jo1.jp", "subject": "✌️😬", "date": "2025-09-27T23:48:50+09:00", "date_ts": 1758984530.0, "preview": "✌️😬 今日も今日とておつかれさま！！ 明日また連絡する！！ おやすみ！！！🫶", "has_attachments": false, "attachments": [], "body_html": " \r\n                             \r\n                            \r\n                            <div id=\"wrap\" style=\"width:100%;margin:0; padding:0; background-color:#ffffff; color:#333333; font-family:sans-serif;text-align:center; line-height:1.7;\">\r\n                            <div id=\"container\" style=\"width:90%; height:auto; background-color:#FFFFFF; margin:0 auto; padding:30px 0; text-align:left;\"><div><div><div>今日も今日とておつかれさま！！<br>\r\n明日また連絡する！！<br>\r\nおやすみ！！！🫶</div>\r\n<div dir=\"auto\"><br>\r\n</div>\r\n<div><img src=\"assets/20250927_2583____/575b68d7f946754e71e.jpeg\" style=\"max-width: 100%;\"></div>\r\n<br clear=\"all\"><br clear=\"all\"><div></div>\r\n</div>\r\n</div>\r\n\r\n</div></div>\r\n"}