{"id": "20250216_2130_taipei__", "from_name": "金城碧海", "from_addr": "sky_kinjo_jo1@mail.jo1.jp", "subject": "taipei 👏", "date": "2025-02-16T16:07:02+09:00", "date_ts": 1739689622.0, "preview": "taipei 👏 超楽しかった！！ けいごくんが餃子食べようとしてたから俺も欲しい！って言ったら 頼んでくれた！ やさ男すぎるぜK-5", "has_attachments": false, "attachments": [], "body_html": " \r\n                             \r\n                            \r\n                            <div id=\"wrap\" style=\"width:100%;margin:0; padding:0; background-color:#ffffff; color:#333333; font-family:sans-serif;text-align:center; line-height:1.7;\">\r\n                            <div id=\"container\" style=\"width:90%; height:auto; background-color:#FFFFFF; margin:0 auto; padding:30px 0; text-align:left;\"><div><div><div dir=\"auto\">超楽しかった！！</div>\r\n<div dir=\"auto\">けいごくんが餃子食べようとしてたから俺も欲しい！って言ったら </div>\r\n<div dir=\"auto\">頼んでくれた！</div>\r\n<div dir=\"auto\">やさ男すぎるぜK-5</div>\r\n<br clear=\"all\"><div><img src=\"assets/20250216_2130_taipei__/2da967b18e7f18ced1e.jpeg\" style=\"max-width: 100%;\"></div>\r\n<div><img src=\"assets/20250216_2130_taipei__/2da967b18e7f18ced2e.jpeg\" style=\"max-width: 100%;\"></div>\r\n<br clear=\"all\"><div></div>\r\n</div>\r\n</div>\r\n\r\n</div></div>\r\n"}